{
  "type": "minecraft:block",
  "pools": [
    {
      "bonus_rolls": 0.0,
      "conditions": [
        {
          "block": "cheesus:grey_cheese",
          "condition": "minecraft:block_state_property",
          "properties": {
            "bites": "0"
          }
        },
        {
          "condition": "minecraft:match_tool",
          "predicate": {
            "enchantments": [
              {
                "enchantment": "minecraft:silk_touch",
                "levels": {
                  "min": 1
                }
              }
            ]
          }
        }
      ],
      "entries": [
        {
          "type": "minecraft:item",
          "name": "cheesus:grey_cheese"
        }
      ],
      "rolls": 1.0
    },
    {
      "bonus_rolls": 0.0,
      "conditions": [
        {
          "condition": "minecraft:all_of",
          "terms": [
            {
              "block": "cheesus:grey_cheese",
              "condition": "minecraft:block_state_property",
              "properties": {
                "bites": "0"
              }
            },
            {
              "condition": "minecraft:inverted",
              "term": {
                "condition": "minecraft:match_tool",
                "predicate": {
                  "enchantments": [
                    {
                      "enchantment": "minecraft:silk_touch",
                      "levels": {
                        "min": 1
                      }
                    }
                  ]
                }
              }
            }
          ]
        }
      ],
      "entries": [
        {
          "type": "minecraft:item",
          "name": "cheesus:grey_cheese_slice"
        }
      ],
      "rolls": 4.0
    },
    {
      "bonus_rolls": 0.0,
      "conditions": [
        {
          "block": "cheesus:grey_cheese",
          "condition": "minecraft:block_state_property",
          "properties": {
            "bites": "1"
          }
        }
      ],
      "entries": [
        {
          "type": "minecraft:item",
          "name": "cheesus:grey_cheese_slice"
        }
      ],
      "rolls": 3.0
    },
    {
      "bonus_rolls": 0.0,
      "conditions": [
        {
          "block": "cheesus:grey_cheese",
          "condition": "minecraft:block_state_property",
          "properties": {
            "bites": "2"
          }
        }
      ],
      "entries": [
        {
          "type": "minecraft:item",
          "name": "cheesus:grey_cheese_slice"
        }
      ],
      "rolls": 2.0
    },
    {
      "bonus_rolls": 0.0,
      "conditions": [
        {
          "block": "cheesus:grey_cheese",
          "condition": "minecraft:block_state_property",
          "properties": {
            "bites": "3"
          }
        }
      ],
      "entries": [
        {
          "type": "minecraft:item",
          "name": "cheesus:grey_cheese_slice"
        }
      ],
      "rolls": 1.0
    }
  ],
  "random_sequence": "cheesus:blocks/grey_cheese"
}